thistle/__init__.py
thistle/_version.py
thistle/alpha5.py
thistle/cli.py
thistle/io.py
thistle/propagator.py
thistle/typing.py
thistle/utils.py
thistle-0.1.0rc7.dist-info/METADATA
thistle-0.1.0rc7.dist-info/WHEEL
thistle-0.1.0rc7.dist-info/RECORD
