Metadata-Version: 2.4
Name: thistle
Version: 0.1.0rc7
Summary: A wrapper for sgp4 that handles TLE switching
Author-email: Jonathan Olsten <jonathan.olsten@gmail.com>
Requires-Python: >=3.9
Requires-Dist: click>=8.1.8
Requires-Dist: numpy>=1.22
Requires-Dist: platformdirs>=4.3.7
Requires-Dist: sgp4>=2.23
Requires-Dist: skyfield>=1.53
Requires-Dist: tqdm>=4.67.1
